crystalpy_barno/__init__.py
crystalpy_barno/entry_point.py
crystalpy_barno/enums.py
crystalpy_barno/config/__init__.py
crystalpy_barno/config/database_config.py
crystalpy_barno/helpers/__init__.py
crystalpy_barno/helpers/database_helper.py
crystalpy_barno/helpers/report_loader_helper.py
crystalpy_barno/helpers/report_parameter_helper.py
crystalpy_barno/helpers/CR/CrystalDecisions.CrystalReports.Engine.dll
crystalpy_barno/helpers/CR/CrystalDecisions.Shared.dll
crystalpy_barno/helpers/CR/CrystalDecisions.Windows.Forms.dll
crystalpy_barno/helpers/CR/__init__.py
crystalpy_barno/reports/__init__.py
crystalpy_barno/reports/base_report.py
crystalpy_barno/reports/report_factory.py
crystalpy_barno-1.1.26.dist-info/licenses/LICENSE
tests/rpt/__init__.py
crystalpy_barno-1.1.26.dist-info/METADATA
crystalpy_barno-1.1.26.dist-info/WHEEL
crystalpy_barno-1.1.26.dist-info/top_level.txt
crystalpy_barno-1.1.26.dist-info/RECORD
